{
    "name" : "ocredit-phones-admin-guns-db-binlog-source",
    "config":
    {
        "connector.class": "io.debezium.connector.mysql.MySqlConnector",
        "database.hostname": "10.52.5.214",
        "database.port": "20000",
        "database.user": "dw_read_only",
        "database.password": "y^n#^qk3",
        "database.server.id": "202004021651",
        "database.server.name": "ocredit_db_admin_guns",
        "database.whitelist": "admin_guns",
        "table.whitelist": "admin_guns.sys_user,admin_guns.sys_dept",
        "event.deserialization.failure.handling.mode": "warn",
        "transforms":"unwrap,insertuuid",
        "transforms.unwrap.type":"io.debezium.transforms.ExtractNewRecordState",
        "transforms.unwrap.operation.header":"true",
        "transforms.unwrap.drop.tombstones":"false",
        "transforms.unwrap.delete.handling.mode":"rewrite",
        "transforms.unwrap.operation.header":true,
        "transforms.unwrap.add.source.fields":"table,version,connector,name,ts_ms,db,server_id,file,pos,row",
        "transforms.insertuuid.type":"com.github.cjmatta.kafka.connect.smt.InsertUuid$Value",
        "transforms.insertuuid.uuid.field.name":"uuid",
        "database.history.kafka.bootstrap.servers": "10.52.5.208:9092,10.52.5.209:9092,10.52.5.210:9092",
        "database.history.kafka.topic": "dbhistory.ocredit_db_admin_guns",
        "database.history.kafka.recovery.poll.interval.ms":100000,
        "database.history.store.only.monitored.tables.ddl":"true",
        "include.schema.changes": "true",
        "snapshot.locking.mode": "none",
        "decimal.handling.mode": "double",
        "include.query":"false",
        "tombstones.on.delete":"false",
        "snapshot.mode":"when_needed",
        "database.serverTimezone":"UTC",
        "database.history.skip.unparseable.ddl":"true"
    }
}
